usrnamegen/__init__.py
usrnamegen/words/adjectives.txt
usrnamegen/words/blacklist.txt
usrnamegen/words/nouns.txt
usrnamegen-0.5.0.dist-info/METADATA
usrnamegen-0.5.0.dist-info/WHEEL
usrnamegen-0.5.0.dist-info/licenses/LICENSE
usrnamegen-0.5.0.dist-info/RECORD
