Metadata-Version: 2.3
Name: usrnamegen
Version: 0.5.0
Summary: Generate random usernames
Project-URL: homepage, https://github.com/lifr0m/usrnamegen
Author: Lifr0m
License: MIT License
Keywords: generator,username
Classifier: License :: OSI Approved :: MIT License
Classifier: Operating System :: OS Independent
Classifier: Programming Language :: Python :: 3
Classifier: Typing :: Typed
Requires-Python: >=3.13
Provides-Extra: dev
Requires-Dist: mypy; extra == 'dev'
Requires-Dist: ruff; extra == 'dev'
